.gitignore
CHANGES.rst
MANIFEST.in
README.rst
bootstrap.py
setup.py
iw/__init__.py
iw.rejectanonymous.egg-info/PKG-INFO
iw.rejectanonymous.egg-info/SOURCES.txt
iw.rejectanonymous.egg-info/dependency_links.txt
iw.rejectanonymous.egg-info/entry_points.txt
iw.rejectanonymous.egg-info/namespace_packages.txt
iw.rejectanonymous.egg-info/not-zip-safe
iw.rejectanonymous.egg-info/requires.txt
iw.rejectanonymous.egg-info/top_level.txt
iw/rejectanonymous/__init__.py
iw/rejectanonymous/configure.zcml
iw/rejectanonymous/plonecontrolpanel.py
iw/rejectanonymous/utils.py
iw/rejectanonymous/doctests/README.txt
iw/rejectanonymous/tests/__init__.py
iw/rejectanonymous/tests/base.py
iw/rejectanonymous/tests/test_rejectanonymousdocs.py