Metadata-Version: 1.1
Name: iw.rejectanonymous
Version: 1.2.5
Summary: Disallow access to a Plone site and its children if user is anonymous
Home-page: https://svn.plone.org/svn/collective/iw.rejectanonymous
Author: Ingeniweb
Author-email: support@ingeniweb.com
License: GPL
Keywords: plone extranet
Platform: UNKNOWN
Classifier: Framework :: Plone
Classifier: Framework :: Plone :: 3.2
Classifier: Framework :: Plone :: 3.3
Classifier: Framework :: Plone :: 4.0
Classifier: Framework :: Plone :: 4.1
Classifier: Framework :: Plone :: 5.0
Classifier: Framework :: Plone :: 5.1
Classifier: Framework :: Plone :: 5.2
Classifier: Framework :: Zope2
Classifier: Programming Language :: Python
Classifier: Topic :: Software Development :: Libraries :: Python Modules
